blihtz/__init__.py
blihtz/__version__.py
blihtz/blihtz.py
blihtz/exceptions.py
blihtz/key.py
blihtz/repository.py
blihtz-0.0.2.dist-info/LICENSE.md
blihtz-0.0.2.dist-info/METADATA
blihtz-0.0.2.dist-info/WHEEL
blihtz-0.0.2.dist-info/top_level.txt
blihtz-0.0.2.dist-info/RECORD
